MANIFEST.in
README.rst
setup.py
docs/HISTORY.txt
docs/LICENSE.GPL
docs/LICENSE.rst
rapido/__init__.py
rapido.souper.egg-info/PKG-INFO
rapido.souper.egg-info/SOURCES.txt
rapido.souper.egg-info/dependency_links.txt
rapido.souper.egg-info/entry_points.txt
rapido.souper.egg-info/namespace_packages.txt
rapido.souper.egg-info/not-zip-safe
rapido.souper.egg-info/requires.txt
rapido.souper.egg-info/top_level.txt
rapido/souper/__init__.py
rapido/souper/catalog.py
rapido/souper/configure.zcml
rapido/souper/interfaces.py
rapido/souper/locator.py
rapido/souper/record.py
rapido/souper/soup.py
rapido/souper/soup.rst
rapido/souper/tests.py