Metadata-Version: 1.1
Name: rapido.souper
Version: 1.0.4
Summary: Souper persistence for Rapido
Home-page: https://github.com/collective/rapido.souper
Author: Eric BREHAULT
Author-email: ebrehault@gmail.com
License: GPL
Keywords: souper zodb rapido
Platform: UNKNOWN
Classifier: Programming Language :: Python
